programlib/__init__.py
programlib/agent.py
programlib/language.py
programlib/pexpectutil.py
programlib/program.py
programlib/programs/.gitkeep
programlib/terminal.py
programlib-12.0.5.dist-info/LICENSE
programlib-12.0.5.dist-info/METADATA
programlib-12.0.5.dist-info/WHEEL
programlib-12.0.5.dist-info/RECORD
