Metadata-Version: 2.1
Name: programlib
Version: 12.0.5
Summary: Programs as Objects
License: MIT
Author: Vadim Liventsev
Author-email: dev@vadim.me
Requires-Python: >=3.8,<4.0
Classifier: Intended Audience :: Developers
Classifier: Intended Audience :: Science/Research
Classifier: License :: OSI Approved :: MIT License
Classifier: Programming Language :: Python :: 3
Classifier: Programming Language :: Python :: 3.8
Classifier: Programming Language :: Python :: 3.9
Classifier: Programming Language :: Python :: 3.10
Classifier: Programming Language :: Python :: 3.11
Classifier: Programming Language :: Python :: 3.12
Classifier: Topic :: Software Development :: Compilers
Requires-Dist: contextlib-chdir (>=1.0.2,<2.0.0) ; python_version < "3.11"
Requires-Dist: numpy (>=1.22.4,<2.0.0)
Requires-Dist: pexpect (>=4.8.0,<5.0.0)
Requires-Dist: pyte (>=0.8.0,<0.9.0)
